<?xml version="1.0" encoding="utf-8" ?>
<dwsync>
<file name="content-single.php" server="ftp.helenelcg.com//" local="130966039924252693" remote="130954553400000000" Dst="1" />
<file name="content.php" server="ftp.helenelcg.com//" local="130966039924267709" remote="130954553400000000" Dst="1" />
<file name="footer.php" server="ftp.helenelcg.com//" local="130966039929099675" remote="130954553400000000" Dst="1" />
<file name="functions.php" server="ftp.helenelcg.com//" local="130966039930826043" remote="130954553400000000" Dst="1" />
<file name="header.php" server="ftp.helenelcg.com//" local="130966039930826043" remote="130954571400000000" Dst="1" />
<file name="home-template.php" server="ftp.helenelcg.com//" local="130966039930836096" remote="130954553400000000" Dst="1" />
<file name="index.php" server="ftp.helenelcg.com//" local="130966039935219269" remote="130954553400000000" Dst="1" />
<file name="sidebar.php" server="ftp.helenelcg.com//" local="130966039935229331" remote="130954553400000000" Dst="1" />
<file name="style.css" server="ftp.helenelcg.com//" local="130966039935903932" remote="130954576200000000" Dst="1" />
</dwsync>